[
  {
    "timestamp": "2025-02-26T20:52:12.031100",
    "query": "who was the best in the c league this month",
    "response": "When you ask about 'who was the best in the c league this month', which division/league are you referring to? We have divisions 1, 2, 3 in our database.",
    "context": {
      "original_query": "who was the best in the c league this month",
      "location": null,
      "division_breakdown": false,
      "format": "default",
      "time_period": "month",
      "time_filter": "date >= DATE_TRUNC('month', CURRENT_DATE) AND date < DATE_TRUNC('month', CURRENT_DATE) + INTERVAL '1 month'",
      "awaiting_clarification": true,
      "clarification_type": "division"
    }
  }
]